Workbook

Sheet Resumo
A1: RESUMO — CUSTO DE MATERIAIS, EQUIPAMENTOS E EPI (sem mão de obra)
A3: Item | B3: Grupo | C3: Total (R$) | D3: % do total
A4: 3.0 | B4: DEMOLIÇÕES | C4: =SUMPRODUCT((LEFT(Materiais!$A$2:$A$126,2)="3.")*Materiais!$K$2:$K$126) | D4: =IFERROR(C4/$C$17,0)
A5: 7.0 | B5: FECHAMENTOS (tela, tijolo de vidro, chapa perfurada, muro de vidro) | C5: =SUMPRODUCT((LEFT(Materiais!$A$2:$A$126,2)="7.")*Materiais!$K$2:$K$126) | D5: =IFERROR(C5/$C$17,0)
A6: 9.0 | B6: ILUMINAÇÃO | C6: =SUMPRODUCT((LEFT(Materiais!$A$2:$A$126,2)="9.")*Materiais!$K$2:$K$126) | D6: =IFERROR(C6/$C$17,0)
A7: 10.0 | B7: PINTURA / ACABAMENTOS | C7: =SUMPRODUCT((LEFT(Materiais!$A$2:$A$126,3)="10.")*Materiais!$K$2:$K$126) | D7: =IFERROR(C7/$C$17,0)
A8: 12.0 | B8: REVESTIMENTOS DE PAREDE (Fulget, moldura, ACM) | C8: =SUMPRODUCT((LEFT(Materiais!$A$2:$A$126,3)="12.")*Materiais!$K$2:$K$126) | D8: =IFERROR(C8/$C$17,0)
A9: 14.0 | B9: ESQUADRIAS / TELAS | C9: =SUMPRODUCT((LEFT(Materiais!$A$2:$A$126,3)="14.")*Materiais!$K$2:$K$126) | D9: =IFERROR(C9/$C$17,0)
A10: 18.0 | B10: IMPERMEABILIZAÇÃO | C10: =SUMPRODUCT((LEFT(Materiais!$A$2:$A$126,3)="18.")*Materiais!$K$2:$K$126) | D10: =IFERROR(C10/$C$17,0)
A11: 23.0 | B11: TELHADOS – CALHAS E RUFOS | C11: =SUMPRODUCT((LEFT(Materiais!$A$2:$A$126,3)="23.")*Materiais!$K$2:$K$126) | D11: =IFERROR(C11/$C$17,0)
B12: Subtotal materiais (deve bater com a aba Materiais) | C12: =SUM(C4:C11) | D12: =IFERROR(C12/$C$17,0)
B13: Equipamentos, andaimes, plataformas e ferramentas | C13: =Equipamentos!$G$26 | D13: =IFERROR(C13/$C$17,0)
B14: EPI, EPC e treinamentos | C14: ='EPI-EPC'!$F$28 | D14: =IFERROR(C14/$C$17,0)
B15: Soma | C15: =C12+C13+C14 | D15: =IFERROR(C15/$C$17,0)
B16: Contingência | C16: =C15*Premissas!$C$24 | D16: =IFERROR(C16/$C$17,0)
B17: TOTAL GERAL (sem mão de obra, BDI e impostos) | C17: =C15+C16 | D17: =IFERROR(C17/$C$17,0)
C18: =IF(ABS(C12-Materiais!$K$128)<0.01,"OK – confere com aba Materiais","CONFERIR")
A20: Observações:
A21: • Preços de referência São Paulo (capital), out/2026, sem frete e sem mão de obra. Cotar com 3 fornecedores antes de fechar.
A22: • Chapa perfurada usa 104 m² (conferido nas plantas) e não os 80 m² da planilha – ajustar em Premissas se quiser.
A23: • Item 12.04: a planilha diz "remoção" da moldura EPS, mas o projeto manda INSTALAR moldura em todos os caixilhos – orçado como fornecimento.
A24: • Muro de vidro (7.05) e calhas (23.01) costumam ser contratados como fornecimento + instalação – compare com a soma de material desta planilha.
A25: • Forro (10.01/10.02) e área de caixilhos (10.03) foram ASSUMIDOS – medir no local.

Sheet Premissas
A1: LEVANTAMENTO DE MATERIAIS — REFORMA DE FACHADA UNIVERSIDADE SÃO CAMILO (IPIRANGA)
A2: Células em amarelo/azul são editáveis. Todas as quantidades das outras abas são calculadas a partir daqui.
A3: Ref | B3: Premissa | C3: Valor | D3: Unid. | E3: Origem / observação
A4: 4 | B4: Área Fulget cinza médio (item 12.01) | C4: 1830.4 | D4: m² | E4: Planilha do cliente, item 12.01
A5: 5 | B5: Área Fulget cinza claro – torre (12.02) | C5: 53.83 | D5: m² | E5: Planilha do cliente, item 12.02
A6: 6 | B6: Área Fulget vermelho – floreira (12.03) | C6: 2 | D6: m² | E6: Planilha do cliente, item 12.03
A7: 7 | B7: Área de demolição de revestimentos (3.01) | C7: 1884.25 | D7: m² | E7: Planilha do cliente, item 3.01
A8: 8 | B8: ACM vermelho 4 mm (12.05) | C8: 287.84 | D8: m² | E8: Planilha do cliente; levantamento nas plantas ≈ 290 m²
A9: 9 | B9: ACM cinza médio 4 mm (12.06) | C9: 23.47 | D9: m² | E9: Planilha do cliente, item 12.06
A10: 10 | B10: Chapa perfurada moeda (7.04) | C10: 104 | D10: m² | E10: Conferido nas plantas ≈ 104 m² (planilha: 80 m²). Profundidade das bonecas assumida 0,30 m
A11: 11 | B11: Moldura cimentícia EPS 100x30 (12.04) | C11: 1269 | D11: ml | E11: Planilha do cliente (projeto pede INSTALAÇÃO; planilha diz "remoção" – confirmar)
A12: 12 | B12: Tijolo de vidro 200x200x60 ventilado (7.02) | C12: 11 | D12: m² | E12: Planilha do cliente, item 7.02
A13: 13 | B13: Tijolo de vidro 190x190x80 ondulado (7.03) | C13: 5 | D13: m² | E13: Planilha do cliente, item 7.03
A14: 14 | B14: Muro de vidro temperado + alumínio (7.05) | C14: 110 | D14: m² | E14: Planilha do cliente, item 7.05
A15: 15 | B15: Tela anti-pássaros torre (7.01) | C15: 50 | D15: m² | E15: Planilha do cliente, item 7.01
... A19: 19 | B19: Área bruta de fachada (base p/ andaime) | C19: 2125 | D19: m² | E19: Levantamento nas plantas (fachadas c/ janelas, sem muros)
A20: 20 | B20: % da fachada com andaime montado ao mesmo tempo | C20: 0.5 | E20: Andaime avança por trechos/fachadas
A21: 21 | B21: Prazo de obra | C21: 5 | D21: meses | E21: ASSUMIDO
A22: 22 | B22: Equipe média em obra | C22: 10 | D22: pessoas | E22: ASSUMIDO
A23: 23 | B23: Perda padrão de materiais | C23: 0.1 | E23: Usada quando a linha não define outra
A24: 24 | B24: Contingência sobre o total | C24: 0.1 | E24: Reserva para imprevistos
A25: 25 | B25: Espaçamento médio das juntas horizontais do Fulget | C25: 1.85 | D25: m | E25: Projeto: juntas a cada pavimento/faixa (1,61 a 2,00 m)
A28: Preços: referência de mercado em São Paulo (capital), out/2026, material sem mão de obra e sem frete, salvo indicação. São estimativas para orçamento — confirmar com no mínimo 3 cotações antes de fechar.
A29: Referências públicas usadas como âncora: SINAPI 05/2026 (locação de andaime fachadeiro R$ 21,00/m²×mês, média nacional; Fulget moldado in loco R$ 190,10/m² com execução); anúncios de ACM 3 mm 1,22×5 m (≈ R$ 74–101/m²).

Sheet Materiais
A1: Item | B1: Material / insumo | C1: Unid. compra | D1: Base (qtde do serviço) | E1: Unid. base | F1: Consumo por unid. base | G1: Perda | H1: Rendimento por unid. de compra | I1: Qtde a comprar | J1: Preço unit. SP (R$) | K1: Total (R$) | L1: Observação / especificação
A2: 3.0 | B2: DEMOLIÇÕES
A3: 3.01 | B3: Disco diamantado segmentado 110 mm (corte de reboco) | C3: un | D3: =Premissas!$C$7 | E3: m² | F3: 1 | G3: 0 | H3: 60 | I3: =IFERROR(ROUNDUP(D3*F3*(1+G3)/H3,0),0) | J3: 45 | K3: =I3*J3 | L3: 1 disco p/ ~60 m²
A4: 3.01 | B4: Ponteiro e talhadeira SDS-Max p/ martelete | C4: un | D4: =Premissas!$C$7 | E4: m² | F4: 1 | G4: 0 | H4: 120 | I4: =IFERROR(ROUNDUP(D4*F4*(1+G4)/H4,0),0) | J4: 85 | K4: =I4*J4 | L4: Desgaste
A5: 3.01 | B5: Saco de ráfia p/ entulho (60 kg) | C5: un | D5: =Premissas!$C$7 | E5: m² | F5: 0.5 | G5: 0 | H5: 1 | I5: =IFERROR(ROUNDUP(D5*F5*(1+G5)/H5,0),0) | J5: 1.6 | K5: =I5*J5 | L5: Parte do entulho desce pelo tubo coletor direto na caçamba
A6: 3.01 | B6: Lona plástica preta 150 micras (proteção de pisos/floreiras) | C6: m² | D6: =Premissas!$C$7 | E6: m² | F6: 0.3 | G6: =Premissas!$C$23 | H6: 1 | I6: =IFERROR(ROUNDUP(D6*F6*(1+G6)/H6,0),0) | J6: 2.8 | K6: =I6*J6 | L6: Proteção ao pé da fachada
A7: 3.02 | B7: Fita isolante, conectores tipo Wago e caixas p/ guarda dos refletores | C7: vb | D7: 1 | E7: vb | F7: 1 | G7: 0 | H7: 1 | I7: =IFERROR(ROUNDUP(D7*F7*(1+G7)/H7,0),0) | J7: 250 | K7: =I7*J7 | L7: Refletores serão reinstalados
A8: 3.03 | B8: Disco de corte 4.1/2" p/ metal (marquise metálica) | C8: un | D8: 1 | E8: vb | F8: 40 | G8: 0 | H8: 1 | I8: =IFERROR(ROUNDUP(D8*F8*(1+G8)/H8,0),0) | J8: 8.5 | K8: =I8*J8 | L8: Demolição da marquise metálica
A9: 3.03 | B9: Cilindro de oxigênio + acetileno (recarga) p/ oxicorte | C9: un | D9: 1 | E9: vb | F9: 1 | G9: 0 | H9: 1 | I9: =IFERROR(ROUNDUP(D9*F9*(1+G9)/H9,0),0) | J9: 650 | K9: =I9*J9 | L9: Se houver estrutura pesada; opcional
A10: 3.04 | B10: Material p/ desativação elétrica (fita, terminais, conectores, caixas de passagem) | C10: vb | D10: 1 | E10: vb | F10: 1 | G10: 0 | H10: 1 | I10: =IFERROR(ROUNDUP(D10*F10*(1+G10)/H10,0),0) | J10: 450 | K10: =I10*J10
A11: 3.05 | B11: Disco diamantado p/ rasgo em parede/piso (125 mm) | C11: un | D11: 1 | E11: vb | F11: 6 | G11: 0 | H11: 1 | I11: =IFERROR(ROUNDUP(D11*F11*(1+G11)/H11,0),0) | J11: 65 | K11: =I11*J11
A12: 3.05 | B12: Argamassa p/ fechamento de rasgos (saco 20 kg) | C12: sc | D12: 1 | E12: vb | F12: 15 | G12: 0 | H12: 1 | I12: =IFERROR(ROUNDUP(D12*F12*(1+G12)/H12,0),0) | J12: 24 | K12: =I12*J12
A13: 3.06 | B13: Caçamba estacionária 5 m³ (locação + retirada) | C13: un | D13: =Premissas!$C$7 | E13: m² | F13: 0.0325 | G13: 0 | H13: 5 | I13: =IFERROR(ROUNDUP(D13*F13*(1+G13)/H13,0),0) | J13: 480 | K13: =I13*J13 | L13: ≈ 61 m³ de entulho ÷ 5 m³ ≈ 13 caçambas (inclui CTR)
A14: 7.0 | B14: FECHAMENTOS
A15: 7.01 | B15: Tela anti-pássaros (polietileno alta resistência ou aço galvanizado) | C15: m² | D15: =Premissas!$C$15 | E15: m² | F15: 1 | G15: =Premissas!$C$23 | H15: 1 | I15: =IFERROR(ROUNDUP(D15*F15*(1+G15)/H15,0),0) | J15: 28 | K15: =I15*J15
A16: 7.01 | B16: Kit fixação (perfil/cantoneira alumínio, abraçadeiras, buchas, parafusos inox) | C16: m² | D16: =Premissas!$C$15 | E16: m² | F16: 1 | G16: =Premissas!$C$23 | H16: 1 | I16: =IFERROR(ROUNDUP(D16*F16*(1+G16)/H16,0),0) | J16: 18 | K16: =I16*J16
A17: 7.02 | B17: Tijolo de vidro 200x200x60 incolor COM VENTILAÇÃO | C17: un | D17: =Premissas!$C$12 | E17: m² | F17: 25 | G17: =Premissas!$C$23 | H17: 1 | I17: =IFERROR(ROUNDUP(D17*F17*(1+G17)/H17,0),0) | J17: 48 | K17: =I17*J17 | L17: 25 un/m²
A18: 7.02 | B18: Barra de aço CA-60 Ø5 mm (travamento V/H) – barra 12 m | C18: br | D18: =Premissas!$C$12 | E18: m² | F18: 10 | G18: =Premissas!$C$23 | H18: 12 | I18: =IFERROR(ROUNDUP(D18*F18*(1+G18)/H18,0),0) | J18: 22 | K18: =I18*J18 | L18: ≈ 10 m/m²
A19: 7.02 | B19: Argamassa p/ assentamento de bloco de vidro (saco 20 kg) | C19: sc | D19: =Premissas!$C$12 | E19: m² | F19: 25 | G19: =Premissas!$C$23 | H19: 20 | I19: =IFERROR(ROUNDUP(D19*F19*(1+G19)/H19,0),0) | J19: 38 | K19: =I19*J19 | L19: ≈ 25 kg/m²
A20: 7.02 | B20: Espaçadores p/ bloco de vidro | C20: un | D20: =Premissas!$C$12 | E20: m² | F20: 30 | G20: =Premissas!$C$23 | H20: 1 | I20: =IFERROR(ROUNDUP(D20*F20*(1+G20)/H20,0),0) | J20: 0.9 | K20: =I20*J20
A21: 7.03 | B21: Tijolo de vidro 190x190x80 ondulado incolor | C21: un | D21: =Premissas!$C$13 | E21: m² | F21: 25 | G21: =Premissas!$C$23 | H21: 1 | I21: =IFERROR(ROUNDUP(D21*F21*(1+G21)/H21,0),0) | J21: 24 | K21: =I21*J21 | L21: 25 un/m²
A22: 7.03 | B22: Barra de aço CA-60 Ø5 mm – barra 12 m | C22: br | D22: =Premissas!$C$13 | E22: m² | F22: 10 | G22: =Premissas!$C$23 | H22: 12 | I22: =IFERROR(ROUNDUP(D22*F22*(1+G22)/H22,0),0) | J22: 22 | K22: =I22*J22
A23: 7.03 | B23: Argamassa p/ assentamento de bloco de vidro (saco 20 kg) | C23: sc | D23: =Premissas!$C$13 | E23: m² | F23: 25 | G23: =Premissas!$C$23 | H23: 20 | I23: =IFERROR(ROUNDUP(D23*F23*(1+G23)/H23,0),0) | J23: 38 | K23: =I23*J23
A24: 7.04 | B24: Chapa de ferro perfurada furo redondo (moeda) alternado, #16 (1,5 mm), 1,0×2,0 m | C24: ch | D24: =Premissas!$C$10 | E24: m² | F24: 1 | G24: 0.15 | H24: 2 | I24: =IFERROR(ROUNDUP(D24*F24*(1+G24)/H24,0),0) | J24: 390 | K24: =I24*J24 | L24: ≈ R$ 195/m². Perda de recortes 15%
A25: 7.04 | B25: Metalon 30x30 #18 (subestrutura das caixas e bonecas) – barra 6 m | C25: br | D25: =Premissas!$C$10 | E25: m² | F25: 2.5 | G25: =Premissas!$C$23 | H25: 6 | I25: =IFERROR(ROUNDUP(D25*F25*(1+G25)/H25,0),0) | J25: 78 | K25: =I25*J25 | L25: ≈ 2,5 m/m²
A26: 7.04 | B26: Cantoneira 1"x1/8" – barra 6 m (requadro/fixação) | C26: br | D26: =Premissas!$C$10 | E26: m² | F26: 1 | G26: =Premissas!$C$23 | H26: 6 | I26: =IFERROR(ROUNDUP(D26*F26*(1+G26)/H26,0),0) | J26: 62 | K26: =I26*J26
A27: 7.04 | B27: Chumbador/parabolt 3/8" com porca | C27: un | D27: =Premissas!$C$10 | E27: m² | F27: 2 | G27: =Premissas!$C$23 | H27: 1 | I27: =IFERROR(ROUNDUP(D27*F27*(1+G27)/H27,0),0) | J27: 4.2 | K27: =I27*J27 | L27: Caixas removíveis: prever parafuso c/ porca
A28: 7.04 | B28: Fundo anticorrosivo (galão 3,6 L) | C28: gl | D28: =Premissas!$C$10 | E28: m² | F28: 2 | G28: =Premissas!$C$23 | H28: 40 | I28: =IFERROR(ROUNDUP(D28*F28*(1+G28)/H28,0),0) | J28: 175 | K28: =I28*J28 | L28: 2 faces da chapa; ≈ 40 m²/galão
A29: 7.04 | B29: Tinta PU acrílica alifática cinza médio (kit 3,6 L) | C29: kit | D29: =Premissas!$C$10 | E29: m² | F29: 2 | G29: 0.15 | H29: 25 | I29: =IFERROR(ROUNDUP(D29*F29*(1+G29)/H29,0),0) | J29: 320 | K29: =I29*J29 | L29: 2 faces; 2 demãos; ≈ 25 m²/kit/demão… ver obs
A30: 7.04 | B30: Diluente PU (5 L) | C30: gl | D30: =Premissas!$C$10 | E30: m² | F30: 1 | G30: =Premissas!$C$23 | H30: 60 | I30: =IFERROR(ROUNDUP(D30*F30*(1+G30)/H30,0),0) | J30: 120 | K30: =I30*J30
A31: 7.04 | B31: Eletrodo 6013 2,5 mm (kg) / arame MIG | C31: kg | D31: =Premissas!$C$10 | E31: m² | F31: 0.15 | G31: =Premissas!$C$23 | H31: 1 | I31: =IFERROR(ROUNDUP(D31*F31*(1+G31)/H31,0),0) | J31: 38 | K31: =I31*J31
A32: 7.05 | B32: Vidro temperado incolor 10 mm (muro e portões) | C32: m² | D32: =Premissas!$C$14 | E32: m² | F32: 1 | G32: =Premissas!$C$23 | H32: 1 | I32: =IFERROR(ROUNDUP(D32*F32*(1+G32)/H32,0),0) | J32: 290 | K32: =I32*J32 | L32: Normalmente fornecido + instalado por vidraçaria – cotar pacote
A33: 7.05 | B33: Perfil alumínio c/ pintura eletrostática preta (estrutura do muro) | C33: m² | D33: =Premissas!$C$14 | E33: m² | F33: 1 | G33: =Premissas!$C$23 | H33: 1 | I33: =IFERROR(ROUNDUP(D33*F33*(1+G33)/H33,0),0) | J33: 210 | K33: =I33*J33 | L33: Valor por m² de painel
A34: 7.05 | B34: Ferragens, fechaduras, molas e puxadores dos portões de vidro | C34: cj | D34: 1 | E34: vb | F34: 2 | G34: 0 | H34: 1 | I34: =IFERROR(ROUNDUP(D34*F34*(1+G34)/H34,0),0) | J34: 1850 | K34: =I34*J34 | L34: 2 portões (estimado)
A35: 7.05 | B35: Silicone neutro incolor (tubo 280 g) + fita de vedação | C35: tb | D35: =Premissas!$C$14 | E35: m² | F35: 0.5 | G35: =Premissas!$C$23 | H35: 1 | I35: =IFERROR(ROUNDUP(D35*F35*(1+G35)/H35,0),0) | J35: 32 | K35: =I35*J35
A36: 9.0 | B36: ILUMINAÇÃO
A37: 9.02 | B37: Refletor wall washer LED 80 W, 30°, IP66/67, 3000 K – Vista 1 | C37: un | D37: 16 | E37: un | F37: 1 | G37: 0 | H37: 1 | I37: =IFERROR(ROUNDUP(D37*F37*(1+G37)/H37,0),0) | J37: 690 | K37: =I37*J37 | L37: Quantidade da planilha
A38: 9.04 | B38: Refletor wall washer LED 150 W, 30–45°, IP66/67, 3000 K – Vista 2 | C38: un | D38: 22 | E38: un | F38: 1 | G38: 0 | H38: 1 | I38: =IFERROR(ROUNDUP(D38*F38*(1+G38)/H38,0),0) | J38: 1150 | K38: =I38*J38
A39: 9.06 | B39: Refletor wall washer LED 80 W, 30°, IP66/67, 3000 K – Vista 3 | C39: un | D39: 14 | E39: un | F39: 1 | G39: 0 | H39: 1 | I39: =IFERROR(ROUNDUP(D39*F39*(1+G39)/H39,0),0) | J39: 690 | K39: =I39*J39
A40: 9.0 | B40: Cabo PP 3x2,5 mm² (alimentação dos refletores) | C40: m | D40: 52 | E40: un | F40: 15 | G40: =Premissas!$C$23 | H40: 1 | I40: =IFERROR(ROUNDUP(D40*F40*(1+G40)/H40,0),0) | J40: 9.8 | K40: =I40*J40 | L40: ≈ 15 m por refletor (52 refletores)
A41: 9.0 | B41: Eletroduto galvanizado 3/4" + conduletes + abraçadeiras | C41: m | D41: 52 | E41: un | F41: 12 | G41: =Premissas!$C$23 | H41: 1 | I41: =IFERROR(ROUNDUP(D41*F41*(1+G41)/H41,0),0) | J41: 24 | K41: =I41*J41 | L41: ≈ 12 m por refletor
A42: 9.0 | B42: Disjuntores, DR e quadro de comando c/ temporizador/fotocélula | C42: cj | D42: 1 | E42: vb | F42: 3 | G42: 0 | H42: 1 | I42: =IFERROR(ROUNDUP(D42*F42*(1+G42)/H42,0),0) | J42: 1200 | K42: =I42*J42 | L42: 1 circuito por vista
A43: 10.0 | B43: PINTURA / ACABAMENTOS
A44: 10.01 | B44: Massa acrílica (lata 25 kg) – forro existente | C44: lt | D44: =Premissas!$C$17 | E44: m² | F44: 1 | G44: =Premissas!$C$23 | H44: 30 | I44: =IFERROR(ROUNDUP(D44*F44*(1+G44)/H44,0),0) | J44: 165 | K44: =I44*J44 | L44: 2 demãos; ≈ 30 m²/lata
A45: 10.01 | B45: Lixa p/ massa nº 150/180 | C45: un | D45: =Premissas!$C$17 | E45: m² | F45: 0.3 | G45: =Premissas!$C$23 | H45: 1 | I45: =IFERROR(ROUNDUP(D45*F45*(1+G45)/H45,0),0) | J45: 1.6 | K45: =I45*J45
A46: 10.02 | B46: Tinta acrílica fosca branca Coral Rende Muito (18 L) | C46: lt | D46: =Premissas!$C$17 | E46: m² | F46: 2 | G46: =Premissas!$C$23 | H46: 200 | I46: =IFERROR(ROUNDUP(D46*F46*(1+G46)/H46,0),0) | J46: 330 | K46: =I46*J46 | L46: 2 demãos; ≈ 200 m²/lata/demão
A47: 10.02 | B47: Selador acrílico (18 L) | C47: lt | D47: =Premissas!$C$17 | E47: m² | F47: 1 | G47: =Premissas!$C$23 | H47: 100 | I47: =IFERROR(ROUNDUP(D47*F47*(1+G47)/H47,0),0) | J47: 190 | K47: =I47*J47
A48: 10.03 | B48: Fundo antiferruginoso / zarcão (galão 3,6 L) | C48: gl | D48: =Premissas!$C$18 | E48: m² | F48: 1 | G48: =Premissas!$C$23 | H48: 35 | I48: =IFERROR(ROUNDUP(D48*F48*(1+G48)/H48,0),0) | J48: 135 | K48: =I48*J48 | L48: 1 demão
A49: 10.03 | B49: Esmalte sintético preto (galão 3,6 L) | C49: gl | D49: =Premissas!$C$18 | E49: m² | F49: 2 | G49: =Premissas!$C$23 | H49: 40 | I49: =IFERROR(ROUNDUP(D49*F49*(1+G49)/H49,0),0) | J49: 160 | K49: =I49*J49 | L49: 2 demãos
A50: 10.03 | B50: Thinner / aguarrás (5 L) | C50: gl | D50: =Premissas!$C$18 | E50: m² | F50: 1 | G50: =Premissas!$C$23 | H50: 90 | I50: =IFERROR(ROUNDUP(D50*F50*(1+G50)/H50,0),0) | J50: 85 | K50: =I50*J50
A51: 10.03 | B51: Lixa ferro nº 80/120 + escova de aço | C51: un | D51: =Premissas!$C$18 | E51: m² | F51: 0.5 | G51: =Premissas!$C$23 | H51: 1 | I51: =IFERROR(ROUNDUP(D51*F51*(1+G51)/H51,0),0) | J51: 3.5 | K51: =I51*J51
A52: 10.03 | B52: Vidro liso 4 mm p/ reposição (estimado 5% dos vãos) | C52: m² | D52: =Premissas!$C$18 | E52: m² | F52: 0.05 | G52: =Premissas!$C$23 | H52: 1 | I52: =IFERROR(ROUNDUP(D52*F52*(1+G52)/H52,0),0) | J52: 135 | K52: =I52*J52 | L52: Planilha: "trocar se necessário" – conferir na visita
A53: 10.03 | B53: Massa de vidraceiro / silicone p/ vidros | C53: kg | D53: =Premissas!$C$18 | E53: m² | F53: 0.05 | G53: =Premissas!$C$23 | H53: 1 | I53: =IFERROR(ROUNDUP(D53*F53*(1+G53)/H53,0),0) | J53: 18 | K53: =I53*J53
A54: 10.04 | B54: Esmalte sintético vermelho segurança (galão 3,6 L) – hidrantes e portas corta-fogo | C54: gl | D54: 1 | E54: vb | F54: 4 | G54: 0 | H54: 1 | I54: =IFERROR(ROUNDUP(D54*F54*(1+G54)/H54,0),0) | J54: 170 | K54: =I54*J54
A55: 10.04 | B55: Fundo antiferruginoso (galão 3,6 L) | C55: gl | D55: 1 | E55: vb | F55: 2 | G55: 0 | H55: 1 | I55: =IFERROR(ROUNDUP(D55*F55*(1+G55)/H55,0),0) | J55: 135 | K55: =I55*J55
A56: 12.0 | B56: REVESTIMENTOS DE PAREDE
A57: 12.01 | B57: Cimento CP-II 50 kg – chapisco (1:3) | C57: sc | D57: =Premissas!$C$4 | E57: m² | F57: 2.4 | G57: =Premissas!$C$23 | H57: 50 | I57: =IFERROR(ROUNDUP(D57*F57*(1+G57)/H57,0),0) | J57: 39 | K57: =I57*J57 | L57: Chapisco ≈ 2,4 kg cimento/m²
A58: 12.01 | B58: Areia grossa lavada (m³) – chapisco | C58: m³ | D58: =Premissas!$C$4 | E58: m² | F58: 0.0055 | G58: =Premissas!$C$23 | H58: 1 | I58: =IFERROR(ROUNDUP(D58*F58*(1+G58)/H58,0),0) | J58: 175 | K58: =I58*J58
A59: 12.01 | B59: Aditivo adesivo p/ chapisco (tipo Bianco, 18 L) | C59: bd | D59: =Premissas!$C$4 | E59: m² | F59: 0.08 | G59: =Premissas!$C$23 | H59: 18 | I59: =IFERROR(ROUNDUP(D59*F59*(1+G59)/H59,0),0) | J59: 290 | K59: =I59*J59 | L59: ≈ 0,08 L/m²
A60: 12.01 | B60: Cimento CP-II 50 kg – reboco 2,5 cm (traço 1:2:8) | C60: sc | D60: =Premissas!$C$4 | E60: m² | F60: 4.5 | G60: =Premissas!$C$23 | H60: 50 | I60: =IFERROR(ROUNDUP(D60*F60*(1+G60)/H60,0),0) | J60: 39 | K60: =I60*J60 | L60: ≈ 4,5 kg/m² p/ 2,5 cm
A61: 12.01 | B61: Cal hidratada CH-III 20 kg – reboco | C61: sc | D61: =Premissas!$C$4 | E61: m² | F61: 4.5 | G61: =Premissas!$C$23 | H61: 20 | I61: =IFERROR(ROUNDUP(D61*F61*(1+G61)/H61,0),0) | J61: 19 | K61: =I61*J61
A62: 12.01 | B62: Areia média lavada (m³) – reboco | C62: m³ | D62: =Premissas!$C$4 | E62: m² | F62: 0.03 | G62: =Premissas!$C$23 | H62: 1 | I62: =IFERROR(ROUNDUP(D62*F62*(1+G62)/H62,0),0) | J62: 170 | K62: =I62*J62
A63: 12.01 | B63: Aditivo impermeabilizante p/ argamassa (18 L) | C63: bd | D63: =Premissas!$C$4 | E63: m² | F63: 0.1 | G63: =Premissas!$C$23 | H63: 18 | I63: =IFERROR(ROUNDUP(D63*F63*(1+G63)/H63,0),0) | J63: 165 | K63: =I63*J63
A64: 12.01 | B64: Granilha (pedrisco de mármore/granito) nº 0/1 p/ Fulget cinza médio – saco 40 kg | C64: sc | D64: =Premissas!$C$4 | E64: m² | F64: 18 | G64: =Premissas!$C$23 | H64: 40 | I64: =IFERROR(ROUNDUP(D64*F64*(1+G64)/H64,0),0) | J64: 42 | K64: =I64*J64 | L64: ≈ 18 kg/m² (espessura ≈ 1,2 cm)
A65: 12.01 | B65: Cimento branco estrutural 40 kg – Fulget | C65: sc | D65: =Premissas!$C$4 | E65: m² | F65: 6 | G65: =Premissas!$C$23 | H65: 40 | I65: =IFERROR(ROUNDUP(D65*F65*(1+G65)/H65,0),0) | J65: 78 | K65: =I65*J65 | L65: ≈ 6 kg/m²; tom cinza com mistura de cimento cinza conforme amostra
A66: 12.01 | B66: Perfil de junta de dilatação 1" (U) alumínio – barra 6 m | C66: br | D66: =Premissas!$C$4 | E66: m² | F66: =1/Premissas!$C$25 | G66: =Premissas!$C$23 | H66: 6 | I66: =IFERROR(ROUNDUP(D66*F66*(1+G66)/H66,0),0) | J66: 72 | K66: =I66*J66 | L66: Juntas horizontais a cada ≈ 1,85 m (projeto DET.02 indica perfil U em aço 1")
A67: 12.01 | B67: Resina acrílica impermeabilizante p/ Fulget (base solvente, 18 L) | C67: lt | D67: =Premissas!$C$4 | E67: m² | F67: 1 | G67: =Premissas!$C$23 | H67: 70 | I67: =IFERROR(ROUNDUP(D67*F67*(1+G67)/H67,0),0) | J67: 390 | K67: =I67*J67 | L67: 2 demãos; ≈ 70 m²/lata
A68: 12.01 | B68: Ácido muriático diluído p/ limpeza (galão 5 L) | C68: gl | D68: =Premissas!$C$4 | E68: m² | F68: 0.07 | G68: =Premissas!$C$23 | H68: 5 | I68: =IFERROR(ROUNDUP(D68*F68*(1+G68)/H68,0),0) | J68: 38 | K68: =I68*J68
A69: 12.01 | B69: Tela galvanizada p/ reforço de reboco em encontros/vergas (rolo 50 m × 0,25 m) | C69: rl | D69: =Premissas!$C$4 | E69: m² | F69: 0.02 | G69: =Premissas!$C$23 | H69: 1 | I69: =IFERROR(ROUNDUP(D69*F69*(1+G69)/H69,0),0) | J69: 95 | K69: =I69*J69 | L69: ≈ 1 m de tela a cada 50 m²… ajustar
A70: 12.02 | B70: Cimento CP-II 50 kg – chapisco (1:3) | C70: sc | D70: =Premissas!$C$5 | E70: m² | F70: 2.4 | G70: =Premissas!$C$23 | H70: 50 | I70: =IFERROR(ROUNDUP(D70*F70*(1+G70)/H70,0),0) | J70: 39 | K70: =I70*J70 | L70: Chapisco ≈ 2,4 kg cimento/m²
A71: 12.02 | B71: Areia grossa lavada (m³) – chapisco | C71: m³ | D71: =Premissas!$C$5 | E71: m² | F71: 0.0055 | G71: =Premissas!$C$23 | H71: 1 | I71: =IFERROR(ROUNDUP(D71*F71*(1+G71)/H71,0),0) | J71: 175 | K71: =I71*J71
A72: 12.02 | B72: Aditivo adesivo p/ chapisco (tipo Bianco, 18 L) | C72: bd | D72: =Premissas!$C$5 | E72: m² | F72: 0.08 | G72: =Premissas!$C$23 | H72: 18 | I72: =IFERROR(ROUNDUP(D72*F72*(1+G72)/H72,0),0) | J72: 290 | K72: =I72*J72 | L72: ≈ 0,08 L/m²
A73: 12.02 | B73: Cimento CP-II 50 kg – reboco 2,5 cm (traço 1:2:8) | C73: sc | D73: =Premissas!$C$5 | E73: m² | F73: 4.5 | G73: =Premissas!$C$23 | H73: 50 | I73: =IFERROR(ROUNDUP(D73*F73*(1+G73)/H73,0),0) | J73: 39 | K73: =I73*J73 | L73: ≈ 4,5 kg/m² p/ 2,5 cm
A74: 12.02 | B74: Cal hidratada CH-III 20 kg – reboco | C74: sc | D74: =Premissas!$C$5 | E74: m² | F74: 4.5 | G74: =Premissas!$C$23 | H74: 20 | I74: =IFERROR(ROUNDUP(D74*F74*(1+G74)/H74,0),0) | J74: 19 | K74: =I74*J74
A75: 12.02 | B75: Areia média lavada (m³) – reboco | C75: m³ | D75: =Premissas!$C$5 | E75: m² | F75: 0.03 | G75: =Premissas!$C$23 | H75: 1 | I75: =IFERROR(ROUNDUP(D75*F75*(1+G75)/H75,0),0) | J75: 170 | K75: =I75*J75
A76: 12.02 | B76: Aditivo impermeabilizante p/ argamassa (18 L) | C76: bd | D76: =Premissas!$C$5 | E76: m² | F76: 0.1 | G76: =Premissas!$C$23 | H76: 18 | I76: =IFERROR(ROUNDUP(D76*F76*(1+G76)/H76,0),0) | J76: 165 | K76: =I76*J76
A77: 12.02 | B77: Granilha (pedrisco de mármore/granito) nº 0/1 p/ Fulget cinza claro – saco 40 kg | C77: sc | D77: =Premissas!$C$5 | E77: m² | F77: 18 | G77: =Premissas!$C$23 | H77: 40 | I77: =IFERROR(ROUNDUP(D77*F77*(1+G77)/H77,0),0) | J77: 42 | K77: =I77*J77 | L77: ≈ 18 kg/m² (espessura ≈ 1,2 cm)
A78: 12.02 | B78: Cimento branco estrutural 40 kg – Fulget | C78: sc | D78: =Premissas!$C$5 | E78: m² | F78: 6 | G78: =Premissas!$C$23 | H78: 40 | I78: =IFERROR(ROUNDUP(D78*F78*(1+G78)/H78,0),0) | J78: 78 | K78: =I78*J78 | L78: ≈ 6 kg/m²; tom cinza com mistura de cimento cinza conforme amostra
A79: 12.02 | B79: Perfil de junta de dilatação 1" (U) alumínio – barra 6 m | C79: br | D79: =Premissas!$C$5 | E79: m² | F79: =1/Premissas!$C$25 | G79: =Premissas!$C$23 | H79: 6 | I79: =IFERROR(ROUNDUP(D79*F79*(1+G79)/H79,0),0) | J79: 72 | K79: =I79*J79 | L79: Juntas horizontais a cada ≈ 1,85 m (projeto DET.02 indica perfil U em aço 1")
A80: 12.02 | B80: Resina acrílica impermeabilizante p/ Fulget (base solvente, 18 L) | C80: lt | D80: =Premissas!$C$5 | E80: m² | F80: 1 | G80: =Premissas!$C$23 | H80: 70 | I80: =IFERROR(ROUNDUP(D80*F80*(1+G80)/H80,0),0) | J80: 390 | K80: =I80*J80 | L80: 2 demãos; ≈ 70 m²/lata
A81: 12.02 | B81: Ácido muriático diluído p/ limpeza (galão 5 L) | C81: gl | D81: =Premissas!$C$5 | E81: m² | F81: 0.07 | G81: =Premissas!$C$23 | H81: 5 | I81: =IFERROR(ROUNDUP(D81*F81*(1+G81)/H81,0),0) | J81: 38 | K81: =I81*J81
A82: 12.02 | B82: Tela galvanizada p/ reforço de reboco em encontros/vergas (rolo 50 m × 0,25 m) | C82: rl | D82: =Premissas!$C$5 | E82: m² | F82: 0.02 | G82: =Premissas!$C$23 | H82: 1 | I82: =IFERROR(ROUNDUP(D82*F82*(1+G82)/H82,0),0) | J82: 95 | K82: =I82*J82 | L82: ≈ 1 m de tela a cada 50 m²… ajustar
A83: 12.03 | B83: Cimento CP-II 50 kg – chapisco (1:3) | C83: sc | D83: =Premissas!$C$6 | E83: m² | F83: 2.4 | G83: =Premissas!$C$23 | H83: 50 | I83: =IFERROR(ROUNDUP(D83*F83*(1+G83)/H83,0),0) | J83: 39 | K83: =I83*J83 | L83: Chapisco ≈ 2,4 kg cimento/m²
A84: 12.03 | B84: Areia grossa lavada (m³) – chapisco | C84: m³ | D84: =Premissas!$C$6 | E84: m² | F84: 0.0055 | G84: =Premissas!$C$23 | H84: 1 | I84: =IFERROR(ROUNDUP(D84*F84*(1+G84)/H84,0),0) | J84: 175 | K84: =I84*J84
A85: 12.03 | B85: Aditivo adesivo p/ chapisco (tipo Bianco, 18 L) | C85: bd | D85: =Premissas!$C$6 | E85: m² | F85: 0.08 | G85: =Premissas!$C$23 | H85: 18 | I85: =IFERROR(ROUNDUP(D85*F85*(1+G85)/H85,0),0) | J85: 290 | K85: =I85*J85 | L85: ≈ 0,08 L/m²
A86: 12.03 | B86: Cimento CP-II 50 kg – reboco 2,5 cm (traço 1:2:8) | C86: sc | D86: =Premissas!$C$6 | E86: m² | F86: 4.5 | G86: =Premissas!$C$23 | H86: 50 | I86: =IFERROR(ROUNDUP(D86*F86*(1+G86)/H86,0),0) | J86: 39 | K86: =I86*J86 | L86: ≈ 4,5 kg/m² p/ 2,5 cm
A87: 12.03 | B87: Cal hidratada CH-III 20 kg – reboco | C87: sc | D87: =Premissas!$C$6 | E87: m² | F87: 4.5 | G87: =Premissas!$C$23 | H87: 20 | I87: =IFERROR(ROUNDUP(D87*F87*(1+G87)/H87,0),0) | J87: 19 | K87: =I87*J87
A88: 12.03 | B88: Areia média lavada (m³) – reboco | C88: m³ | D88: =Premissas!$C$6 | E88: m² | F88: 0.03 | G88: =Premissas!$C$23 | H88: 1 | I88: =IFERROR(ROUNDUP(D88*F88*(1+G88)/H88,0),0) | J88: 170 | K88: =I88*J88
A89: 12.03 | B89: Aditivo impermeabilizante p/ argamassa (18 L) | C89: bd | D89: =Premissas!$C$6 | E89: m² | F89: 0.1 | G89: =Premissas!$C$23 | H89: 18 | I89: =IFERROR(ROUNDUP(D89*F89*(1+G89)/H89,0),0) | J89: 165 | K89: =I89*J89
A90: 12.03 | B90: Granilha (pedrisco de mármore/granito) nº 0/1 p/ Fulget vermelho – saco 40 kg | C90: sc | D90: =Premissas!$C$6 | E90: m² | F90: 18 | G90: =Premissas!$C$23 | H90: 40 | I90: =IFERROR(ROUNDUP(D90*F90*(1+G90)/H90,0),0) | J90: 42 | K90: =I90*J90 | L90: ≈ 18 kg/m² (espessura ≈ 1,2 cm)
A91: 12.03 | B91: Cimento branco estrutural 40 kg – Fulget (base p/ pigmento) | C91: sc | D91: =Premissas!$C$6 | E91: m² | F91: 6 | G91: =Premissas!$C$23 | H91: 40 | I91: =IFERROR(ROUNDUP(D91*F91*(1+G91)/H91,0),0) | J91: 78 | K91: =I91*J91 | L91: ≈ 6 kg/m²; tom cinza com mistura de cimento cinza conforme amostra
A92: 12.03 | B92: Pigmento óxido de ferro vermelho (kg) | C92: kg | D92: =Premissas!$C$6 | E92: m² | F92: 0.6 | G92: =Premissas!$C$23 | H92: 1 | I92: =IFERROR(ROUNDUP(D92*F92*(1+G92)/H92,0),0) | J92: 28 | K92: =I92*J92
A93: 12.03 | B93: Perfil de junta de dilatação 1" (U) alumínio – barra 6 m | C93: br | D93: =Premissas!$C$6 | E93: m² | F93: =1/Premissas!$C$25 | G93: =Premissas!$C$23 | H93: 6 | I93: =IFERROR(ROUNDUP(D93*F93*(1+G93)/H93,0),0) | J93: 72 | K93: =I93*J93 | L93: Juntas horizontais a cada ≈ 1,85 m (projeto DET.02 indica perfil U em aço 1")
A94: 12.03 | B94: Resina acrílica impermeabilizante p/ Fulget (base solvente, 18 L) | C94: lt | D94: =Premissas!$C$6 | E94: m² | F94: 1 | G94: =Premissas!$C$23 | H94: 70 | I94: =IFERROR(ROUNDUP(D94*F94*(1+G94)/H94,0),0) | J94: 390 | K94: =I94*J94 | L94: 2 demãos; ≈ 70 m²/lata
A95: 12.03 | B95: Ácido muriático diluído p/ limpeza (galão 5 L) | C95: gl | D95: =Premissas!$C$6 | E95: m² | F95: 0.07 | G95: =Premissas!$C$23 | H95: 5 | I95: =IFERROR(ROUNDUP(D95*F95*(1+G95)/H95,0),0) | J95: 38 | K95: =I95*J95
A96: 12.03 | B96: Tela galvanizada p/ reforço de reboco em encontros/vergas (rolo 50 m × 0,25 m) | C96: rl | D96: =Premissas!$C$6 | E96: m² | F96: 0.02 | G96: =Premissas!$C$23 | H96: 1 | I96: =IFERROR(ROUNDUP(D96*F96*(1+G96)/H96,0),0) | J96: 95 | K96: =I96*J96 | L96: ≈ 1 m de tela a cada 50 m²… ajustar
A97: 12.04 | B97: Moldura cimentícia EPS 100x30 mm (barra 1,0 m) | C97: br | D97: =Premissas!$C$11 | E97: ml | F97: 1 | G97: =Premissas!$C$23 | H97: 1 | I97: =IFERROR(ROUNDUP(D97*F97*(1+G97)/H97,0),0) | J97: 26 | K97: =I97*J97 | L97: Projeto prevê instalação em todos os caixilhos
A98: 12.04 | B98: Argamassa colante / cola PU p/ fixação da moldura (saco 20 kg) | C98: sc | D98: =Premissas!$C$11 | E98: ml | F98: 0.6 | G98: =Premissas!$C$23 | H98: 20 | I98: =IFERROR(ROUNDUP(D98*F98*(1+G98)/H98,0),0) | J98: 32 | K98: =I98*J98
A99: 12.04 | B99: Tinta acrílica cinza claro p/ moldura (18 L) | C99: lt | D99: =Premissas!$C$11 | E99: ml | F99: 0.25 | G99: =Premissas!$C$23 | H99: 180 | I99: =IFERROR(ROUNDUP(D99*F99*(1+G99)/H99,0),0) | J99: 360 | K99: =I99*J99 | L99: 0,25 m² pintado por ml; 2 demãos inclusas no rendimento
A100: 12.05 | B100: Painel ACM 4 mm vermelho institucional São Camilo (chapa 1,25×5,0 m) | C100: m² | D100: =Premissas!$C$8 | E100: m² | F100: 1 | G100: 0.15 | H100: 1 | I100: =IFERROR(ROUNDUP(D100*F100*(1+G100)/H100,0),0) | J100: 165 | K100: =I100*J100 | L100: Cor especial: cotar com amostra. Perda de dobras/cortes 15%
...

Sheet Equipamentos
A1: Item | B1: Equipamento / locação | C1: Unid. | D1: Qtde | E1: Períodos (meses/vezes) | F1: Preço unit. SP (R$) | G1: Total (R$) | H1: Observação
A2: 1 | B2: Andaime fachadeiro tubular – locação (m² de fachada × mês) | C2: m²×mês | D2: =Premissas!$C$19*Premissas!$C$20 | E2: =Premissas!$C$21-1 | F2: 23 | G2: =D2*E2*F2 | H2: SINAPI 05/2026 média nacional R$ 21,00/m²×mês; SP costuma ficar entre R$ 18 e R$ 28. Sem montagem
A3: 2 | B3: Montagem + desmontagem de andaime (mão de obra da locadora) | C3: m² | D3: =Premissas!$C$19 | E3: 1 | F3: 9 | G3: =D3*E3*F3 | H3: Mobilização por trecho; confirmar se a locadora inclui
A4: 3 | B4: Tela fachadeira de proteção (polietileno, rolo 3×50 m) – EPC NR-18 | C4: m² | D4: =Premissas!$C$19*Premissas!$C$20 | E4: 1 | F4: 4.2 | G4: =D4*E4*F4 | H4: Compra; reaproveitada entre trechos
A5: 4 | B5: Plataforma elevatória articulada 15–16 m (diesel) | C5: mês | D5: 1 | E5: 2 | F5: 15500 | G5: =D5*E5*F5 | H5: ACM, calhas, refletores e pontos sem andaime; + frete abaixo
A6: 5 | B6: Frete ida/volta plataforma articulada | C6: vez | D6: 1 | E6: 1 | F6: 2200 | G6: =D6*E6*F6
A7: 6 | B7: Plataforma tesoura elétrica 10–12 m | C7: mês | D7: 1 | E7: 3 | F7: 5800 | G7: =D7*E7*F7 | H7: Pátios internos (Vistas 4, 5, 6)
A8: 7 | B8: Frete ida/volta plataforma tesoura | C8: vez | D8: 1 | E8: 1 | F8: 1100 | G8: =D8*E8*F8
A9: 8 | B9: Tubo coletor de entulho (duto) c/ funil – locação | C9: mês | D9: 1 | E9: 2 | F9: 850 | G9: =D9*E9*F9 | H9: Descida do entulho da demolição direto na caçamba
A10: 9 | B10: Guincho de coluna / elevador de carga 300 kg | C10: mês | D10: 1 | E10: =Premissas!$C$21-1 | F10: 1350 | G10: =D10*E10*F10 | H10: Subida de argamassa e Fulget
A11: 10 | B11: Betoneira 400 L | C11: mês | D11: 2 | E11: =Premissas!$C$21-1 | F11: 480 | G11: =D11*E11*F11
A12: 11 | B12: Martelete rompedor 10 kg | C12: mês | D12: 3 | E12: 2 | F12: 680 | G12: =D12*E12*F12 | H12: Fase de demolição
A13: 12 | B13: Lavadora de alta pressão (lavagem do Fulget) | C13: mês | D13: 2 | E13: =Premissas!$C$21-2 | F13: 380 | G13: =D13*E13*F13
A14: 13 | B14: Container almoxarifado/escritório | C14: mês | D14: 1 | E14: =Premissas!$C$21 | F14: 1150 | G14: =D14*E14*F14
A15: 14 | B15: Banheiro químico (c/ higienização semanal) | C15: mês | D15: 2 | E15: =Premissas!$C$21 | F15: 690 | G15: =D15*E15*F15 | H15: NR-18: 1 p/ cada 20 trabalhadores
A16: 15 | B16: Tapume compensado resinado 10 mm 2,20×1,10 (isolamento do passeio) | C16: ch | D16: 60 | E16: 1 | F16: 98 | G16: =D16*E16*F16 | H16: Compra
A17: 16 | B17: Esmerilhadeira 4.1/2" | C17: un | D17: 3 | E17: 1 | F17: 390 | G17: =D17*E17*F17 | H17: Compra
A18: 17 | B18: Furadeira de impacto / parafusadeira | C18: un | D18: 4 | E18: 1 | F18: 520 | G18: =D18*E18*F18 | H18: Compra
A19: 18 | B19: Serra circular c/ disco p/ ACM + tupia c/ fresa V (dobra do ACM) | C19: cj | D19: 1 | E19: 1 | F19: 1900 | G19: =D19*E19*F19 | H19: Compra
A20: 19 | B20: Máquina de solda inversora 200 A | C20: un | D20: 1 | E20: 1 | F20: 1250 | G20: =D20*E20*F20 | H20: Compra
A21: 20 | B21: Ferramentas manuais (desempenadeiras aço/PVC, colheres, réguas alumínio 2 m, prumos, níveis, mangueira de nível) | C21: cj | D21: 1 | E21: 1 | F21: 2800 | G21: =D21*E21*F21 | H21: Compra
A22: 21 | B22: Carrinho de mão, pás, enxadas, baldes, masseiras | C22: cj | D22: 1 | E22: 1 | F22: 1650 | G22: =D22*E22*F22 | H22: Compra
A23: 22 | B23: Extensões elétricas, quadro provisório de obra, refletores de obra | C23: cj | D23: 1 | E23: 1 | F23: 1800 | G23: =D23*E23*F23 | H23: Compra
A24: 23 | B24: Mangueira 50 m, escovas, esponjas, rolos, pincéis, fita crepe, estopa | C24: cj | D24: 1 | E24: 1 | F24: 1400 | G24: =D24*E24*F24 | H24: Consumíveis gerais
F26: TOTAL EQUIPAMENTOS | G26: =SUM(G2:G24)

Sheet EPI-EPC
A1: Item | B1: EPI / EPC | C1: Unid. | D1: Qtde | E1: Preço unit. SP (R$) | F1: Total (R$) | G1: Observação
A2: EPI | B2: Capacete classe B c/ jugular | C2: un | D2: =Premissas!$C$22+2 | E2: 48 | F2: =D2*E2 | G2: +2 p/ visitantes
A3: EPI | B3: Cinto paraquedista NR-35 c/ talabarte duplo e absorvedor | C3: un | D3: =ROUNDUP(Premissas!$C$22*0.8,0) | E3: 430 | F3: =D3*E3 | G3: Todos que trabalham em altura
A4: EPI | B4: Trava-quedas p/ corda 12 mm (linha de vida vertical) | C4: un | D4: =ROUNDUP(Premissas!$C$22*0.4,0) | E4: 380 | F4: =D4*E4
A5: EPC | B5: Corda de poliamida 12 mm p/ linha de vida | C5: m | D5: 300 | E5: 9.5 | F5: =D5*E5
A6: EPI | B6: Óculos de proteção ampla visão | C6: un | D6: =Premissas!$C$22*2 | E6: 19 | F6: =D6*E6
A7: EPI | B7: Protetor auricular tipo plug (par) | C7: par | D7: =Premissas!$C$22*10 | E7: 2.2 | F7: =D7*E7
A8: EPI | B8: Luva de vaqueta | C8: par | D8: =Premissas!$C$22*6 | E8: 19 | F8: =D8*E8
A9: EPI | B9: Luva nitrílica / PVC (cimento, ácido, resina) | C9: par | D9: =Premissas!$C$22*6 | E9: 13 | F9: =D9*E9
A10: EPI | B10: Botina de segurança bico composite | C10: par | D10: Premissas!$C$22 | E10: 145 | F10: =D10*E10
A11: EPI | B11: Bota de PVC cano longo (lavagem do Fulget) | C11: par | D11: =ROUNDUP(Premissas!$C$22*0.5,0) | E11: 72 | F11: =D11*E11
A12: EPI | B12: Máscara PFF2 (poeira de demolição e cimento) | C12: un | D12: =Premissas!$C$22*30 | E12: 4.6 | F12: =D12*E12
A13: EPI | B13: Respirador semifacial + filtro químico (PU, solventes, resina) | C13: un | D13: 4 | E13: 145 | F13: =D13*E13
A14: EPI | B14: Filtro de reposição p/ respirador | C14: un | D14: 16 | E14: 48 | F14: =D14*E14
A15: EPI | B15: Uniforme (camisa manga longa + calça), 2 jogos por pessoa | C15: jg | D15: =Premissas!$C$22*2 | E15: 120 | F15: =D15*E15
A16: EPI | B16: Protetor solar FPS 50 (frasco 1 L) | C16: un | D16: =Premissas!$C$22 | E16: 62 | F16: =D16*E16
A17: EPI | B17: Capa de chuva | C17: un | D17: Premissas!$C$22 | E17: 38 | F17: =D17*E17
A18: EPI | B18: Máscara de solda automática + avental e luva de raspa | C18: cj | D18: 2 | E18: 320 | F18: =D18*E18
A19: EPC | B19: Cone de sinalização 75 cm | C19: un | D19: 20 | E19: 46 | F19: =D19*E19
A20: EPC | B20: Fita zebrada (rolo 200 m) | C20: rl | D20: 10 | E20: 26 | F20: =D20*E20
A21: EPC | B21: Placas de sinalização de obra / NR-26 | C21: un | D21: 12 | E21: 38 | F21: =D21*E21
A22: EPC | B22: Extintor PQS 4 kg + suporte | C22: un | D22: 2 | E22: 190 | F22: =D22*E22
A23: EPC | B23: Kit de primeiros socorros | C23: un | D23: 1 | E23: 160 | F23: =D23*E23
A24: EPC | B24: Guarda-corpo e rodapé extra p/ plataformas e acessos (madeira/metal) | C24: vb | D24: 1 | E24: 1500 | F24: =D24*E24
A25: Treinamento | B25: Treinamento NR-35 (trabalho em altura) + NR-18 por trabalhador | C25: pessoa | D25: Premissas!$C$22 | E25: 260 | F25: =D25*E25 | G25: Obrigatório
A26: Treinamento | B26: Treinamento operador de PEMT (plataforma elevatória) | C26: pessoa | D26: 2 | E26: 480 | F26: =D26*E26 | G26: NR-18/NR-12
E28: TOTAL EPI/EPC | F28: =SUM(F2:F26)
